{"cameraMode":{"drawMode":0,"name":"Shaded","section":"Shading Mode"},"sceneLighting":true,"audioPlay":false,"sceneViewState":{"m_AlwaysRefresh":false,"showFog":true,"showSkybox":true,"showFlares":true,"showImageEffects":true,"showParticleSystems":true,"showVisualEffectGraphs":true,"m_FxEnabled":true},"in2DMode":false,"pivot":{"x":6.391919136047363,"y":10.875561714172364,"z":-0.6309127807617188},"rotation":{"x":0.1223178282380104,"y":-0.2788828909397125,"z":0.03586782142519951,"w":0.9518851637840271},"size":11.847723960876465,"orthographic":false}